gopher/__init__.py
gopher/gopher.py
gopher-0.2.1.dist-info/DESCRIPTION.rst
gopher-0.2.1.dist-info/METADATA
gopher-0.2.1.dist-info/RECORD
gopher-0.2.1.dist-info/WHEEL
gopher-0.2.1.dist-info/entry_points.txt
gopher-0.2.1.dist-info/metadata.json
gopher-0.2.1.dist-info/top_level.txt
