Metadata-Version: 2.0
Name: gopher
Version: 0.2.1
Summary: Download randomized gopher image (png) from gopherize.me
Home-page: https://github.com/taxpon/gopher
Author: Takuro Wada
Author-email: taxpon@gmail.com
License: MIT
Platform: UNKNOWN
Classifier: License :: OSI Approved :: MIT License
Classifier: Programming Language :: Python
Classifier: Topic :: Multimedia :: Graphics
Classifier: Topic :: Utilities
Classifier: Environment :: Console
Requires-Dist: click (>=2.0)
Requires-Dist: requests (>=2.13.0)
Requires-Dist: typing
